[
    {"id":"Backquote","ancho":"2rem","alto":"2rem","posicion":0,"valor":"ª \\","isIcon":false},
    {"id":"Digit1","ancho":"2rem","alto":"2rem","posicion":0,"valor":"1","isIcon":false},
    {"id":"Digit2","ancho":"2rem","alto":"2rem","posicion":0,"valor":"2","isIcon":false},
    {"id":"Digit3","ancho":"2rem","alto":"2rem","posicion":0,"valor":"3","isIcon":false},
    {"id":"Digit4","ancho":"2rem","alto":"2rem","posicion":0,"valor":"4","isIcon":false},
    {"id":"Digit5","ancho":"2rem","alto":"2rem","posicion":0,"valor":"5","isIcon":false},
    {"id":"Digit6","ancho":"2rem","alto":"2rem","posicion":0,"valor":"6","isIcon":false},
    {"id":"Digit7","ancho":"2rem","alto":"2rem","posicion":0,"valor":"7","isIcon":false},
    {"id":"Digit8","ancho":"2rem","alto":"2rem","posicion":0,"valor":"8","isIcon":false},
    {"id":"Digit9","ancho":"2rem","alto":"2rem","posicion":0,"valor":"9","isIcon":false},
    {"id":"Digit0","ancho":"2rem","alto":"2rem","posicion":0,"valor":"0","isIcon":false},
    {"id":"Minus","ancho":"2rem","alto":"2rem","posicion":0,"valor":"'","isIcon":false},
    {"id":"Equal","ancho":"2rem","alto":"2rem","posicion":0,"valor":"¡","isIcon":false},
    {"id":"Backspace","ancho":"4rem","alto":"2rem","posicion":0,"valor":"keyboard_backspace","isIcon":true},
  
    {"id":"Tab","ancho":"3rem","alto":"2rem","posicion":1,"valor":"tab","isIcon":true},
    {"id":"KeyQ","ancho":"2rem","alto":"2rem","posicion":1,"valor":"Q","isIcon":false},
    {"id":"KeyW","ancho":"2rem","alto":"2rem","posicion":1,"valor":"W","isIcon":false},
    {"id":"KeyE","ancho":"2rem","alto":"2rem","posicion":1,"valor":"E","isIcon":false},
    {"id":"KeyR","ancho":"2rem","alto":"2rem","posicion":1,"valor":"R","isIcon":false},
    {"id":"KeyT","ancho":"2rem","alto":"2rem","posicion":1,"valor":"T","isIcon":false},
    {"id":"KeyY","ancho":"2rem","alto":"2rem","posicion":1,"valor":"Y","isIcon":false},
    {"id":"KeyU","ancho":"2rem","alto":"2rem","posicion":1,"valor":"U","isIcon":false},
    {"id":"KeyI","ancho":"2rem","alto":"2rem","posicion":1,"valor":"I","isIcon":false},
    {"id":"KeyO","ancho":"2rem","alto":"2rem","posicion":1,"valor":"O","isIcon":false},
    {"id":"KeyP","ancho":"2rem","alto":"2rem","posicion":1,"valor":"P","isIcon":false},
    {"id":"BracketLeft","ancho":"2rem","alto":"2rem","posicion":1,"valor":"`","isIcon":false},
    {"id":"BracketRight","ancho":"2rem","alto":"2rem","posicion":1,"valor":"+","isIcon":false},
    {"id":"Backslash","ancho":"3rem","alto":"2rem","posicion":1,"valor":"ç","isIcon":false},
  
    {"id":"CapsLock","ancho":"3.5rem","alto":"2rem","posicion":2,"valor":"Bloq","isIcon":false},
    {"id":"KeyA","ancho":"2rem","alto":"2rem","posicion":2,"valor":"A","isIcon":false},
    {"id":"KeyS","ancho":"2rem","alto":"2rem","posicion":2,"valor":"S","isIcon":false},
    {"id":"KeyD","ancho":"2rem","alto":"2rem","posicion":2,"valor":"D","isIcon":false},
    {"id":"KeyF","ancho":"2rem","alto":"2rem","posicion":2,"valor":"F","isIcon":false},
    {"id":"KeyG","ancho":"2rem","alto":"2rem","posicion":2,"valor":"G","isIcon":false},
    {"id":"KeyH","ancho":"2rem","alto":"2rem","posicion":2,"valor":"H","isIcon":false},
    {"id":"KeyJ","ancho":"2rem","alto":"2rem","posicion":2,"valor":"J","isIcon":false},
    {"id":"KeyK","ancho":"2rem","alto":"2rem","posicion":2,"valor":"K","isIcon":false},
    {"id":"KeyL","ancho":"2rem","alto":"2rem","posicion":2,"valor":"L","isIcon":false},
    {"id":"Semicolon","ancho":"2rem","alto":"2rem","posicion":2,"valor":"Ñ","isIcon":false},
    {"id":"Quote","ancho":"2rem","alto":"2rem","posicion":2,"valor":"´","isIcon":false},
    {"id":"Enter","ancho":"4.6rem","alto":"2rem","posicion":2,"valor":"keyboard_return","isIcon":true},
    
    {"id":"ShiftLeft","ancho":"2.5rem","alto":"2rem","posicion":3,"valor":"SHIFT","isIcon":true},
    {"id":"IntlBackslash","ancho":"2rem","alto":"2rem","posicion":3,"valor":"> <","isIcon":false},
    {"id":"KeyZ","ancho":"2rem","alto":"2rem","posicion":3,"valor":"Z","isIcon":false},
    {"id":"KeyX","ancho":"2rem","alto":"2rem","posicion":3,"valor":"X","isIcon":false},
    {"id":"KeyC","ancho":"2rem","alto":"2rem","posicion":3,"valor":"C","isIcon":false},
    {"id":"KeyV","ancho":"2rem","alto":"2rem","posicion":3,"valor":"V","isIcon":false},
    {"id":"KeyB","ancho":"2rem","alto":"2rem","posicion":3,"valor":"B","isIcon":false},
    {"id":"KeyN","ancho":"2rem","alto":"2rem","posicion":3,"valor":"N","isIcon":false},
    {"id":"KeyM","ancho":"2rem","alto":"2rem","posicion":3,"valor":"M","isIcon":false},
    {"id":"Comma","ancho":"2rem","alto":"2rem","posicion":3,"valor":",","isIcon":false},
    {"id":"Period","ancho":"2rem","alto":"2rem","posicion":3,"valor":".","isIcon":false},
    {"id":"Slash","ancho":"2rem","alto":"2rem","posicion":3,"valor":"-","isIcon":false},
    {"id":"ShiftRight","ancho":"5.6rem","alto":"2rem","posicion":3,"valor":"SHIFT","isIcon":true},
    
    {"id":"ControlLeft","ancho":"3rem","alto":"2rem","posicion":4,"valor":"Ctrl","isIcon":false},
    {"id":"window","ancho":"2.5rem","alto":"2rem","posicion":4,"valor":"window","isIcon":true},
    {"id":"AltLeft","ancho":"2.5rem","alto":"2rem","posicion":4,"valor":"Alt","isIcon":false},
    {"id":"Space","ancho":"12.1rem","alto":"2rem","posicion":4,"valor":"","isIcon":false},
    {"id":"AltRight","ancho":"2.5rem","alto":"2rem","posicion":4,"valor":"Alt","isIcon":false},
    {"id":"Fn","ancho":"2.5rem","alto":"2rem","posicion":4,"valor":"Fn","isIcon":false},
    {"id":"menu_","ancho":"2.5rem","alto":"2rem","posicion":4,"valor":"table_rows_narrow","isIcon":true},
    {"id":"ControlRight","ancho":"3rem","alto":"2rem","posicion":4,"valor":"Ctrl","isIcon":false}
]
